README.md
setup.cfg
setup.py
skopos/__init__.py
skopos.egg-info/PKG-INFO
skopos.egg-info/SOURCES.txt
skopos.egg-info/dependency_links.txt
skopos.egg-info/requires.txt
skopos.egg-info/top_level.txt
skopos/agent/__init__.py
skopos/agent/agent.py
skopos/agent/asynch_agent.py
skopos/agent/environment_preprocessing.py
skopos/agent/exploration_strategy.py
skopos/agent/policies.py
skopos/agent/simple_agent.py
skopos/memories/__init__.py
skopos/memories/memory.py
skopos/network/__init__.py
skopos/network/image_layers.py
skopos/network/layers.py
skopos/network/network_builder.py
skopos/network/optimizers.py
skopos/network/recurrent_layers.py
skopos/network/simple_layers.py
skopos/techniques/__init__.py
skopos/techniques/actor_critic.py
skopos/techniques/double_network.py
skopos/techniques/dqn.py
skopos/techniques/dueling_dqn.py
skopos/techniques/learners.py
skopos/techniques/nstep_qlearning.py
skopos/techniques/vanilla_pg.py
skopos/utils/__init__.py
skopos/utils/net_processing.py
skopos/utils/preprocessing.py
skopos/utils/visualize.py