Metadata-Version: 1.1
Name: skopos
Version: 0.3
Summary: Deep Reinforcement Learning Library
Home-page: https://github.com/Skopos-team/Skopos
Author: Skopos-team
Author-email: skopos.library@gmail.com
License: Apache2
Download-URL: https://github.com/Skopos-team/Skopos/archive/0.3.tar.gz
Keywords: testing,logging,example
Platform: UNKNOWN
